README.md
setup.py
naivert/__init__.py
naivert.egg-info/PKG-INFO
naivert.egg-info/SOURCES.txt
naivert.egg-info/dependency_links.txt
naivert.egg-info/requires.txt
naivert.egg-info/top_level.txt
naivert/camera/__init__.py
naivert/camera/camera.py
naivert/geometry/__init__.py
naivert/geometry/face.py
naivert/geometry/get_reflection_halfline.py
naivert/geometry/get_refraction_halfline.py
naivert/geometry/get_tangential_vector.py
naivert/geometry/inter_halfline_face_list.py
naivert/light/__init__.py
naivert/light/light.py
naivert/material/__init__.py
naivert/material/material.py
naivert/scene/__init__.py
naivert/scene/scene.py
naivert/utils/__init__.py
naivert/utils/constant.py
test/test_geometry.py