Metadata-Version: 1.1
Name: naivert
Version: 0.0.1
Summary: A Naive Ray Tracing Implementation
Home-page: https://github.com/GouMinghao/naivert
Author: Minghao Gou
Author-email: gouminghao@gmail.com
License: GPL
Keywords: ray tracing
Platform: UNKNOWN
Classifier: Intended Audience :: Developers
Classifier: Intended Audience :: Education
Classifier: Topic :: Education
Classifier: Topic :: Scientific/Engineering :: Mathematics
Classifier: License :: OSI Approved :: GNU General Public License v3 or later (GPLv3+)
Classifier: Programming Language :: Python :: 3
